{"Longwood":{"crime_score":58.2,"complaints_score":77.7,"crashes_score":55.9,"violations_score":88.1,"overall_score":67.1,"population":5765,"small_pop_warning":false,"crime_count":354,"crime_per_1000":61.4,"complaint_count":16,"complaints_per_1000":2.8,"violations_count":0,"violations_per_1000":0,"crashes_count":55,"crashes_per_1000":9.5,"rank":1},"Jamaica Plain":{"crime_score":55.2,"complaints_score":35.4,"crashes_score":55.3,"violations_score":66.5,"overall_score":52.0,"population":40083,"small_pop_warning":false,"crime_count":12613,"crime_per_1000":314.7,"complaint_count":317,"complaints_per_1000":7.9,"violations_count":69,"violations_per_1000":1.7,"crashes_count":566,"crashes_per_1000":14.1,"rank":10},"Hyde Park":{"crime_score":55.4,"complaints_score":52.0,"crashes_score":55.3,"violations_score":28.4,"overall_score":50.5,"population":33469,"small_pop_warning":false,"crime_count":10022,"crime_per_1000":299.4,"complaint_count":197,"complaints_per_1000":5.9,"violations_count":156,"violations_per_1000":4.7,"crashes_count":483,"crashes_per_1000":14.4,"rank":13},"Charlestown":{"crime_score":56.4,"complaints_score":18.9,"crashes_score":55.4,"violations_score":70.3,"overall_score":48.9,"population":19232,"small_pop_warning":false,"crime_count":4051,"crime_per_1000":210.6,"complaint_count":190,"complaints_per_1000":9.9,"violations_count":26,"violations_per_1000":1.4,"crashes_count":262,"crashes_per_1000":13.6,"rank":16},"West Roxbury":{"crime_score":56.3,"complaints_score":53.7,"crashes_score":56.1,"violations_score":76.7,"overall_score":58.7,"population":33906,"small_pop_warning":false,"crime_count":7359,"crime_per_1000":217.0,"complaint_count":192,"complaints_per_1000":5.7,"violations_count":32,"violations_per_1000":0.9,"crashes_count":269,"crashes_per_1000":7.9,"rank":6},"Mission Hill":{"crime_score":56.8,"complaints_score":81.0,"crashes_score":55.9,"violations_score":38.6,"overall_score":59.9,"population":19076,"small_pop_warning":false,"crime_count":3449,"crime_per_1000":180.8,"complaint_count":45,"complaints_per_1000":2.4,"violations_count":75,"violations_per_1000":3.9,"crashes_count":181,"crashes_per_1000":9.5,"rank":5},"Chinatown":{"crime_score":55.3,"complaints_score":61.9,"crashes_score":56.1,"violations_score":4.3,"overall_score":49.5,"population":6371,"small_pop_warning":false,"crime_count":1925,"crime_per_1000":302.2,"complaint_count":30,"complaints_per_1000":4.7,"violations_count":42,"violations_per_1000":6.6,"crashes_count":53,"crashes_per_1000":8.3,"rank":15},"South Boston":{"crime_score":55.4,"complaints_score":51.2,"crashes_score":55.9,"violations_score":39.8,"overall_score":52.1,"population":38263,"small_pop_warning":false,"crime_count":11225,"crime_per_1000":293.4,"complaint_count":229,"complaints_per_1000":6.0,"violations_count":145,"violations_per_1000":3.8,"crashes_count":372,"crashes_per_1000":9.7,"rank":9},"South Boston Waterfront":{"crime_score":54.6,"complaints_score":24.7,"crashes_score":52.4,"violations_score":77.9,"overall_score":50.2,"population":5300,"small_pop_warning":false,"crime_count":1960,"crime_per_1000":369.8,"complaint_count":49,"complaints_per_1000":9.2,"violations_count":4,"violations_per_1000":0.8,"crashes_count":195,"crashes_per_1000":36.8,"rank":14},"Back Bay":{"crime_score":53.2,"complaints_score":28.8,"crashes_score":55.3,"violations_score":18.2,"overall_score":42.3,"population":18983,"small_pop_warning":false,"crime_count":9142,"crime_per_1000":481.6,"complaint_count":165,"complaints_per_1000":8.7,"violations_count":105,"violations_per_1000":5.5,"crashes_count":278,"crashes_per_1000":14.6,"rank":22},"Dorchester":{"crime_score":54.0,"complaints_score":51.2,"crashes_score":54.5,"violations_score":39.8,"overall_score":51.3,"population":123056,"small_pop_warning":false,"crime_count":51803,"crime_per_1000":421.0,"complaint_count":734,"complaints_per_1000":6.0,"violations_count":464,"violations_per_1000":3.8,"crashes_count":2570,"crashes_per_1000":20.9,"rank":12},"Fenway":{"crime_score":57.4,"complaints_score":82.7,"crashes_score":56.0,"violations_score":79.2,"overall_score":66.7,"population":42351,"small_pop_warning":false,"crime_count":5185,"crime_per_1000":122.4,"complaint_count":92,"complaints_per_1000":2.2,"violations_count":28,"violations_per_1000":0.7,"crashes_count":377,"crashes_per_1000":8.9,"rank":2},"North End":{"crime_score":56.6,"complaints_score":35.4,"crashes_score":56.3,"violations_score":15.7,"overall_score":45.1,"population":10080,"small_pop_warning":false,"crime_count":1963,"crime_per_1000":194.7,"complaint_count":80,"complaints_per_1000":7.9,"violations_count":57,"violations_per_1000":5.7,"crashes_count":61,"crashes_per_1000":6.1,"rank":20},"Roslindale":{"crime_score":57.4,"complaints_score":59.5,"crashes_score":55.7,"violations_score":64.0,"overall_score":58.6,"population":35479,"small_pop_warning":false,"crime_count":4516,"crime_per_1000":127.3,"complaint_count":178,"complaints_per_1000":5.0,"violations_count":68,"violations_per_1000":1.9,"crashes_count":383,"crashes_per_1000":10.8,"rank":7},"Roxbury":{"crime_score":52.8,"complaints_score":57.0,"crashes_score":53.8,"violations_score":36.0,"overall_score":51.5,"population":53821,"small_pop_warning":false,"crime_count":28080,"crime_per_1000":521.7,"complaint_count":287,"complaints_per_1000":5.3,"violations_count":218,"violations_per_1000":4.1,"crashes_count":1394,"crashes_per_1000":25.9,"rank":11},"Allston":{"crime_score":57.3,"complaints_score":79.3,"crashes_score":56.0,"violations_score":60.2,"overall_score":63.0,"population":31810,"small_pop_warning":false,"crime_count":4380,"crime_per_1000":137.7,"complaint_count":83,"complaints_per_1000":2.6,"violations_count":69,"violations_per_1000":2.2,"crashes_count":285,"crashes_per_1000":9.0,"rank":3},"West End":{"crime_score":49.9,"complaints_score":23.0,"crashes_score":52.3,"violations_score":62.7,"overall_score":45.6,"population":5014,"small_pop_warning":false,"crime_count":3866,"crime_per_1000":771.0,"complaint_count":47,"complaints_per_1000":9.4,"violations_count":10,"violations_per_1000":2.0,"crashes_count":190,"crashes_per_1000":37.9,"rank":18},"Harbor Island":{"crime_score":0,"complaints_score":100,"crashes_score":0,"violations_score":88.1,"overall_score":38.2,"population":0,"small_pop_warning":true,"crime_count":11,"crime_per_1000":11000.0,"complaint_count":0,"complaints_per_1000":0,"violations_count":0,"violations_per_1000":0,"crashes_count":1,"crashes_per_1000":1000.0,"rank":23},"Beacon Hill":{"crime_score":56.4,"complaints_score":0.6,"crashes_score":56.3,"violations_score":10.6,"overall_score":35.6,"population":9327,"small_pop_warning":false,"crime_count":1993,"crime_per_1000":213.7,"complaint_count":113,"complaints_per_1000":12.1,"violations_count":57,"violations_per_1000":6.1,"crashes_count":57,"crashes_per_1000":6.1,"rank":24},"Downtown":{"crime_score":49.6,"complaints_score":13.9,"crashes_score":52.6,"violations_score":69.1,"overall_score":44.2,"population":15752,"small_pop_warning":false,"crime_count":12526,"crime_per_1000":795.2,"complaint_count":166,"complaints_per_1000":10.5,"violations_count":24,"violations_per_1000":1.5,"crashes_count":565,"crashes_per_1000":35.9,"rank":21},"Mattapan":{"crime_score":55.5,"complaints_score":51.2,"crashes_score":54.9,"violations_score":17.0,"overall_score":48.5,"population":26796,"small_pop_warning":false,"crime_count":7728,"crime_per_1000":288.4,"complaint_count":162,"complaints_per_1000":6.0,"violations_count":150,"violations_per_1000":5.6,"crashes_count":464,"crashes_per_1000":17.3,"rank":17},"Brighton":{"crime_score":56.5,"complaints_score":67.7,"crashes_score":56.2,"violations_score":62.7,"overall_score":60.2,"population":55869,"small_pop_warning":false,"crime_count":11517,"crime_per_1000":206.1,"complaint_count":226,"complaints_per_1000":4.0,"violations_count":109,"violations_per_1000":2.0,"crashes_count":395,"crashes_per_1000":7.1,"rank":4},"East Boston":{"crime_score":56.0,"complaints_score":70.2,"crashes_score":55.7,"violations_score":37.3,"overall_score":56.7,"population":46892,"small_pop_warning":false,"crime_count":11669,"crime_per_1000":248.8,"complaint_count":172,"complaints_per_1000":3.7,"violations_count":188,"violations_per_1000":4.0,"crashes_count":506,"crashes_per_1000":10.8,"rank":8},"South End":{"crime_score":53.5,"complaints_score":22.2,"crashes_score":55.7,"violations_score":48.7,"overall_score":45.4,"population":35287,"small_pop_warning":false,"crime_count":16341,"crime_per_1000":463.1,"complaint_count":336,"complaints_per_1000":9.5,"violations_count":108,"violations_per_1000":3.1,"crashes_count":400,"crashes_per_1000":11.3,"rank":19}}